cdapsutil/__init__.py
cdapsutil/cd.py
cdapsutil/default_style.cx
cdapsutil/default_style.cx2
cdapsutil/exceptions.py
cdapsutil/fe.py
cdapsutil/runner.py
cdapsutil-0.3.0.data/data/style/default_style.cx
cdapsutil-0.3.0.data/data/style/default_style.cx2
cdapsutil-0.3.0.dist-info/AUTHORS.rst
cdapsutil-0.3.0.dist-info/LICENSE
cdapsutil-0.3.0.dist-info/METADATA
cdapsutil-0.3.0.dist-info/WHEEL
cdapsutil-0.3.0.dist-info/top_level.txt
cdapsutil-0.3.0.dist-info/RECORD
