Metadata-Version: 2.1
Name: cdapsutil
Version: 0.3.0
Summary: Python utilities for CDAPS
Home-page: https://github.com/idekerlab/cdapsutil
Author: Christopher Churas
Author-email: churas.camera@gmail.com
License: BSD license
Keywords: cdapsutil
Classifier: Development Status :: 2 - Pre-Alpha
Classifier: Intended Audience :: Developers
Classifier: License :: OSI Approved :: BSD License
Classifier: Natural Language :: English
Classifier: Programming Language :: Python :: 3
Classifier: Programming Language :: Python :: 3.4
Classifier: Programming Language :: Python :: 3.5
Classifier: Programming Language :: Python :: 3.6
Classifier: Programming Language :: Python :: 3.7
License-File: LICENSE
License-File: AUTHORS.rst
Requires-Dist: ndex2
Requires-Dist: requests
Requires-Dist: tqdm
